nscrapy/__init__.py
nscrapy/get_old.py
nscrapy/nscrap.py
nscrapy/clarin/__init__.py
nscrapy/clarin/clarin.py
nscrapy/lnn/__init__.py
nscrapy/lnn/lnn.py
nscrapy/p12/__init__.py
nscrapy/p12/p12.py
nscrapy-0.0.3.dist-info/LICENSE
nscrapy-0.0.3.dist-info/METADATA
nscrapy-0.0.3.dist-info/WHEEL
nscrapy-0.0.3.dist-info/top_level.txt
nscrapy-0.0.3.dist-info/RECORD
