Metadata-Version: 2.1
Name: nscrapy
Version: 0.0.3
Summary: A small example package for scrapping argentinian newsletters
Home-page: https://github.com/carabedo
Author: carabedo
Author-email: carabedo@gmail.com
License: UNKNOWN
Platform: UNKNOWN
Classifier: Programming Language :: Python :: 3
Classifier: License :: OSI Approved :: MIT License
Classifier: Operating System :: OS Independent
Requires-Python: >=3.7
